aiogram_tool/__init__.py
aiogram_tool/callback_data/__init__.py
aiogram_tool/callback_data/filter.py
aiogram_tool/callback_data/storage.py
aiogram_tool/depend/__init__.py
aiogram_tool/depend/components/__init__.py
aiogram_tool/depend/components/exit.py
aiogram_tool/depend/components/handler.py
aiogram_tool/depend/components/inner_middleware.py
aiogram_tool/depend/depend.py
aiogram_tool/depend/setup.py
aiogram_tool/depend/types/__init__.py
aiogram_tool/depend/types/enums.py
aiogram_tool/depend/types/schema.py
aiogram_tool/depend/utils/__init__.py
aiogram_tool/depend/utils/depend_scope.py
aiogram_tool/depend/utils/explore_obj.py
aiogram_tool/depend/utils/inject_callback.py
aiogram_tool/limit/__init__.py
aiogram_tool/limit/limit.py
aiogram_tool/limit/setup.py
aiogram_tool/limit/storage/__init__.py
aiogram_tool/limit/storage/abstract_storage.py
aiogram_tool/limit/storage/memory_storage.py
aiogram_tool/limit/storage/redis_storage.py
aiogram_tool/limit/utils/__init__.py
aiogram_tool/limit/utils/callback.py
aiogram_tool-1.2.1.dist-info/LICENSE.md
aiogram_tool-1.2.1.dist-info/METADATA
aiogram_tool-1.2.1.dist-info/WHEEL
aiogram_tool-1.2.1.dist-info/RECORD
